Metadata-Version: 2.1
Name: distributions-20240529
Version: 0.1
Summary: Gaussian distributions
